plone.app.contentrules-5.0.8-py3.13-nspkg.pth
plone/app/contentrules/__init__.py
plone/app/contentrules/api.py
plone/app/contentrules/configure.zcml
plone/app/contentrules/handlers.py
plone/app/contentrules/namechooser.py
plone/app/contentrules/rule.py
plone/app/contentrules/testing.py
plone/app/contentrules/actions/__init__.py
plone/app/contentrules/actions/configure.zcml
plone/app/contentrules/actions/copy.py
plone/app/contentrules/actions/delete.py
plone/app/contentrules/actions/logger.py
plone/app/contentrules/actions/mail.py
plone/app/contentrules/actions/move.py
plone/app/contentrules/actions/notify.py
plone/app/contentrules/actions/versioning.py
plone/app/contentrules/actions/workflow.py
plone/app/contentrules/actions/templates/mail.pt
plone/app/contentrules/browser/__init__.py
plone/app/contentrules/browser/adding.py
plone/app/contentrules/browser/assignments.py
plone/app/contentrules/browser/configure.zcml
plone/app/contentrules/browser/controlpanel.py
plone/app/contentrules/browser/elements.py
plone/app/contentrules/browser/formhelper.py
plone/app/contentrules/browser/info.py
plone/app/contentrules/browser/interfaces.py
plone/app/contentrules/browser/navigation.py
plone/app/contentrules/browser/rule.py
plone/app/contentrules/browser/traversal.py
plone/app/contentrules/browser/templates/contentrules-pageform.pt
plone/app/contentrules/browser/templates/controlpanel.pt
plone/app/contentrules/browser/templates/manage-assignments.pt
plone/app/contentrules/browser/templates/manage-elements.pt
plone/app/contentrules/conditions/__init__.py
plone/app/contentrules/conditions/configure.zcml
plone/app/contentrules/conditions/fileextension.py
plone/app/contentrules/conditions/group.py
plone/app/contentrules/conditions/portaltype.py
plone/app/contentrules/conditions/role.py
plone/app/contentrules/conditions/talesexpression.py
plone/app/contentrules/conditions/wfstate.py
plone/app/contentrules/conditions/wftransition.py
plone/app/contentrules/exportimport/__init__.py
plone_app_contentrules-5.0.8.dist-info/METADATA
plone_app_contentrules-5.0.8.dist-info/WHEEL
plone_app_contentrules-5.0.8.dist-info/namespace_packages.txt
plone_app_contentrules-5.0.8.dist-info/top_level.txt
plone_app_contentrules-5.0.8.dist-info/RECORD
