Metadata-Version: 2.4
Name: plone.app.contentrules
Version: 5.0.8
Summary: Plone integration for plone.contentrules
Home-page: https://pypi.org/project/plone.app.contentrules
Author: Plone Foundation
Author-email: plone-developers@lists.sourceforge.net
License: GPL version 2
Keywords: plone automatic content rules
Classifier: Development Status :: 5 - Production/Stable
Classifier: Environment :: Web Environment
Classifier: Framework :: Plone
Classifier: Framework :: Plone :: 6.0
Classifier: Framework :: Plone :: Core
Classifier: Framework :: Zope :: 5
Classifier: License :: OSI Approved :: GNU General Public License v2 (GPLv2)
Classifier: Operating System :: OS Independent
Classifier: Programming Language :: Python
Classifier: Programming Language :: Python :: 3.8
Classifier: Programming Language :: Python :: 3.9
Classifier: Programming Language :: Python :: 3.10
Classifier: Programming Language :: Python :: 3.11
Requires-Python: >=3.8
Requires-Dist: lxml
Requires-Dist: plone.app.contenttypes
Requires-Dist: plone.app.uuid
Requires-Dist: plone.app.vocabularies
Requires-Dist: plone.autoform
Requires-Dist: plone.base
Requires-Dist: plone.contentrules
Requires-Dist: plone.memoize
Requires-Dist: plone.stringinterp
Requires-Dist: plone.supermodel
Requires-Dist: plone.uuid
Requires-Dist: Products.PluggableAuthService
Requires-Dist: Products.GenericSetup
Requires-Dist: Products.MailHost
Requires-Dist: Products.statusmessages
Requires-Dist: setuptools
Requires-Dist: z3c.form
Requires-Dist: Zope
Provides-Extra: test
Requires-Dist: plone.app.testing; extra == "test"
Requires-Dist: plone.app.contenttypes[test]; extra == "test"
Requires-Dist: plone.dexterity; extra == "test"
Requires-Dist: plone.testing; extra == "test"
Dynamic: author
Dynamic: author-email
Dynamic: classifier
Dynamic: description
Dynamic: description-content-type
Dynamic: home-page
Dynamic: keywords
Dynamic: license
Dynamic: provides-extra
Dynamic: requires-dist
Dynamic: requires-python
Dynamic: summary
